.gitignore
LICENSE.txt
MANIFEST.in
NOTICE.txt
README.rst
requirements.txt
setup.cfg
setup.py
cabalgata/__init__.py
cabalgata/zookeeper/__init__.py
cabalgata/zookeeper/catalog.py
cabalgata/zookeeper/plugin.py
cabalgata/zookeeper/util/__init__.py
cabalgata_zookeeper.egg-info/PKG-INFO
cabalgata_zookeeper.egg-info/SOURCES.txt
cabalgata_zookeeper.egg-info/dependency_links.txt
cabalgata_zookeeper.egg-info/entry_points.txt
cabalgata_zookeeper.egg-info/not-zip-safe
cabalgata_zookeeper.egg-info/requires.txt
cabalgata_zookeeper.egg-info/top_level.txt
test/test_catalog.py
test/test_plugin.py
test/test_util.py
test/test_zookeeper.py