Metadata-Version: 1.0
Name: cabalgata-zookeeper
Version: 0.1.1
Summary: A simple wrapper for installing and starting zookeeper services.
Home-page: http://github.com/cabalgata/cabalgata-zookeeper/
Author: Alan D. Cabrera
Author-email: adc@toolazydogs.com
License: Apache Software License (http://www.apache.org/licenses/LICENSE-2.0)
Platform: any
Classifier: Intended Audience :: Developers
Classifier: License :: OSI Approved :: Apache Software License
Classifier: Operating System :: OS Independent
Classifier: Programming Language :: Python
Classifier: Programming Language :: Python :: 2.6
Classifier: Programming Language :: Python :: 2.7
Classifier: Topic :: Software Development :: Libraries :: Python Modules
